layman_terminal/__init__.py
layman_terminal/agent.py
layman_terminal/cli.py
layman_terminal/initialize_config.py
layman_terminal/utils/__init__.py
layman_terminal/utils/prompt_templates.yaml
layman_terminal-0.1.0b6.dist-info/licenses/LICENSE
layman_terminal-0.1.0b6.dist-info/METADATA
layman_terminal-0.1.0b6.dist-info/WHEEL
layman_terminal-0.1.0b6.dist-info/entry_points.txt
layman_terminal-0.1.0b6.dist-info/top_level.txt
layman_terminal-0.1.0b6.dist-info/RECORD
