Metadata-Version: 2.4
Name: layman_terminal
Version: 0.1.0b6
Summary: AI-powered terminal assistant
Home-page: https://github.com/prashantgavit/layman-terminal
Author: Prashant Gavit
Author-email: prashantgavit115@gmail.com
Project-URL: Bug Tracker, https://github.com/prashantgavit/layman-terminal/issues
Keywords: ai terminal cli assistant
Classifier: Development Status :: 4 - Beta
Classifier: Intended Audience :: Developers
Classifier: License :: OSI Approved :: MIT License
Classifier: Programming Language :: Python :: 3.9
Classifier: Programming Language :: Python :: 3.10
Classifier: Programming Language :: Python :: 3.11
Requires-Python: >=3.9
License-File: LICENSE
Requires-Dist: python-dotenv
Requires-Dist: pyyaml
Requires-Dist: google-genai
Dynamic: author
Dynamic: author-email
Dynamic: classifier
Dynamic: description
Dynamic: description-content-type
Dynamic: home-page
Dynamic: keywords
Dynamic: license-file
Dynamic: project-url
Dynamic: requires-dist
Dynamic: requires-python
Dynamic: summary
